HISTORY.md
time2relax/__init__.py
time2relax/exceptions.py
time2relax/models.py
time2relax/time2relax.py
time2relax/utils.py
time2relax-0.7.0.dist-info/LICENSE.txt
time2relax-0.7.0.dist-info/METADATA
time2relax-0.7.0.dist-info/WHEEL
time2relax-0.7.0.dist-info/RECORD
