Metadata-Version: 2.1
Name: time2relax
Version: 0.7.0
Summary: A CouchDB driver for Python.
Home-page: https://github.com/rwanyoike/time2relax-python-driver
License: MIT
Author: Raymond Wanyoike
Author-email: raymond.wanyoike@gmail.com
Requires-Python: >=3.8,<4.0
Classifier: License :: OSI Approved :: MIT License
Classifier: Programming Language :: Python :: 3
Classifier: Programming Language :: Python :: 3.8
Classifier: Programming Language :: Python :: 3.9
Classifier: Programming Language :: Python :: 3.10
Classifier: Programming Language :: Python :: 3.11
Classifier: Programming Language :: Python :: 3.12
Requires-Dist: requests (>=2.32.3,<3.0.0)
Project-URL: Documentation, https://github.com/rwanyoike/time2relax-python-driver/tree/main/docs
Project-URL: Repository, https://github.com/rwanyoike/time2relax-python-driver
